chatllama/__init__.py
chatllama/llama_model.py
chatllama/langchain_modules/__init__.py
chatllama/langchain_modules/prompt_templates.py
chatllama/rlhf/__init__.py
chatllama/rlhf/actor.py
chatllama/rlhf/config.py
chatllama/rlhf/dataset.py
chatllama/rlhf/model_list.py
chatllama/rlhf/model_loader.py
chatllama/rlhf/reward.py
chatllama/rlhf/trainer.py
chatllama/rlhf/utils.py
chatllama_py-0.0.4.dist-info/LICENSE
chatllama_py-0.0.4.dist-info/METADATA
chatllama_py-0.0.4.dist-info/WHEEL
chatllama_py-0.0.4.dist-info/top_level.txt
chatllama_py-0.0.4.dist-info/RECORD
