Metadata-Version: 2.1
Name: chatllama-py
Version: 0.0.4
License-File: LICENSE
Requires-Dist: accelerate
Requires-Dist: beartype
Requires-Dist: deepspeed
Requires-Dist: einops
Requires-Dist: fairscale
Requires-Dist: langchain (>=0.0.103)
Requires-Dist: torch
Requires-Dist: tqdm
Requires-Dist: transformers
Requires-Dist: datasets
Requires-Dist: openai
Requires-Dist: plotly
